turbx/__init__.py
turbx/asymptotic.py
turbx/bl.py
turbx/blasius.py
turbx/cli.py
turbx/composite_profile.py
turbx/compressible_transform.py
turbx/confidence_interval.py
turbx/eas3.py
turbx/eas4.py
turbx/fig_ax_constructor.py
turbx/freestream_parameters.py
turbx/gradient.py
turbx/grid_metric.py
turbx/h5.py
turbx/rgd.py
turbx/rgd_lambda2.py
turbx/rgd_mean.py
turbx/rgd_testing.py
turbx/rgd_xpln_ccor.py
turbx/rgd_xpln_coh.py
turbx/rgd_xpln_mean_dim.py
turbx/rgd_xpln_spectrum.py
turbx/rgd_xpln_stats.py
turbx/rgd_xpln_turb_budget.py
turbx/set_mpl_env.py
turbx/signal.py
turbx/spd.py
turbx/spd_wall_ccor.py
turbx/spd_wall_ci.py
turbx/spd_wall_import.py
turbx/spd_wall_spectrum.py
turbx/spd_wall_stats.py
turbx/utils.py
turbx/ztmd.py
turbx/ztmd_analysis.py
turbx/ztmd_comp_trafo.py
turbx/ztmd_curvilinear.py
turbx/ztmd_loader.py
turbx-1.1.1.dist-info/LICENSE
turbx-1.1.1.dist-info/METADATA
turbx-1.1.1.dist-info/WHEEL
turbx-1.1.1.dist-info/entry_points.txt
turbx-1.1.1.dist-info/top_level.txt
turbx-1.1.1.dist-info/RECORD
