Metadata-Version: 2.2
Name: turbx
Version: 1.1.1
Summary: Extensible toolkit for analyzing turbulent flow datasets
Author: Jason A
Maintainer: Jason A
License: MIT
Keywords: turbulence,fluid mechanics,DNS,MPI,HPC
Classifier: License :: OSI Approved :: MIT License
Classifier: Development Status :: 4 - Beta
Classifier: Intended Audience :: Science/Research
Classifier: Programming Language :: Python :: 3 :: Only
Classifier: Topic :: Scientific/Engineering :: Physics
Classifier: Topic :: System :: Distributed Computing
Classifier: Topic :: Database
Requires-Python: >=3.11
License-File: LICENSE
Requires-Dist: mpi4py>=4.0
Requires-Dist: numpy>=2.0
Requires-Dist: scipy>=1.14
Requires-Dist: h5py>=3.11
Requires-Dist: matplotlib>=3.9
Requires-Dist: tqdm>=4.66
Requires-Dist: psutil>=6.0
Provides-Extra: dev
Requires-Dist: ruff>=0.6; extra == "dev"
Requires-Dist: pytest>=8.0; extra == "dev"
Requires-Dist: pyright>=1.1; extra == "dev"
